apitester/__init__.py
apitester/exceptions.py
apitester/py.typed
apitester/ai/__init__.py
apitester/ai/assistant.py
apitester/ai/base.py
apitester/ai/integrations.py
apitester/cli/__init__.py
apitester/cli/ai.py
apitester/cli/completion.py
apitester/cli/config_manager.py
apitester/cli/debug_commands.py
apitester/cli/environment.py
apitester/cli/help.py
apitester/cli/history.py
apitester/cli/main.py
apitester/cli/request.py
apitester/cli/template.py
apitester/config/__init__.py
apitester/config/defaults.yaml
apitester/config/settings.py
apitester/config/validation.py
apitester/core/__init__.py
apitester/core/cache_manager.py
apitester/core/debug.py
apitester/core/env_manager.py
apitester/core/env_operations.py
apitester/core/error_handler.py
apitester/core/graphql_client.py
apitester/core/history_manager.py
apitester/core/history_query.py
apitester/core/http_client.py
apitester/core/logging.py
apitester/core/monitoring.py
apitester/core/request_validator.py
apitester/core/template_executor.py
apitester/core/template_importer.py
apitester/core/template_manager.py
apitester/core/variable_substitution.py
apitester/formatters/__init__.py
apitester/formatters/response_formatter.py
apitester/formatters/response_saver.py
apitester/formatters/table_formatter.py
apitester/storage/__init__.py
apitester/storage/models.py
apitester/storage/operations.py
apitester/storage/redis_client.py
vesper_reqflow-1.0.0.dist-info/licenses/LICENSE
vesper_reqflow-1.0.0.dist-info/METADATA
vesper_reqflow-1.0.0.dist-info/WHEEL
vesper_reqflow-1.0.0.dist-info/entry_points.txt
vesper_reqflow-1.0.0.dist-info/top_level.txt
vesper_reqflow-1.0.0.dist-info/RECORD
