Metadata-Version: 2.4
Name: vesper-reqflow
Version: 1.0.0
Summary: A Postman-like terminal tool for API testing with Redis backend and AI assistance
Home-page: https://github.com/apitester/agentic-api-tester-cli
Author: API Tester Team
Author-email: ReqFlow Team <team@reqflow.dev>
Maintainer-email: ReqFlow Team <team@reqflow.dev>
License-Expression: MIT
Project-URL: Homepage, https://github.com/VesperAkshay/ReqFlow
Project-URL: Documentation, https://github.com/VesperAkshay/ReqFlow/docs
Project-URL: Repository, https://github.com/VesperAkshay/ReqFlow
Project-URL: Bug Tracker, https://github.com/VesperAkshay/ReqFlow/issues
Keywords: api,testing,http,rest,graphql,postman,cli,terminal,redis,cache,history,templates,environment,ai,assistant
Classifier: Development Status :: 4 - Beta
Classifier: Intended Audience :: Developers
Classifier: Operating System :: OS Independent
Classifier: Programming Language :: Python :: 3
Classifier: Programming Language :: Python :: 3.8
Classifier: Programming Language :: Python :: 3.9
Classifier: Programming Language :: Python :: 3.10
Classifier: Programming Language :: Python :: 3.11
Classifier: Programming Language :: Python :: 3.12
Classifier: Topic :: Software Development :: Testing
Classifier: Topic :: Internet :: WWW/HTTP
Classifier: Topic :: System :: Networking
Classifier: Topic :: Utilities
Classifier: Environment :: Console
Classifier: Typing :: Typed
Requires-Python: >=3.8
License-File: LICENSE
Requires-Dist: typer[all]>=0.9.0
Requires-Dist: rich>=13.0.0
Requires-Dist: httpx>=0.24.0
Requires-Dist: redis>=4.5.0
Requires-Dist: pydantic>=1.10.0
Requires-Dist: PyYAML>=6.0.0
Requires-Dist: python-dotenv>=1.0.0
Requires-Dist: click>=8.1.0
Requires-Dist: dataclasses-json>=0.5.0
Provides-Extra: ai
Requires-Dist: openai>=0.27.0; extra == "ai"
Requires-Dist: anthropic>=0.3.0; extra == "ai"
Requires-Dist: google-generativeai>=0.1.0; extra == "ai"
Provides-Extra: test
Requires-Dist: pytest>=7.0.0; extra == "test"
Requires-Dist: pytest-cov>=4.0.0; extra == "test"
Requires-Dist: pytest-mock>=3.10.0; extra == "test"
Requires-Dist: pytest-xdist>=3.0.0; extra == "test"
Requires-Dist: fakeredis>=2.10.0; extra == "test"
Requires-Dist: responses>=0.23.0; extra == "test"
Provides-Extra: dev
Requires-Dist: pytest>=7.0.0; extra == "dev"
Requires-Dist: pytest-cov>=4.0.0; extra == "dev"
Requires-Dist: pytest-mock>=3.10.0; extra == "dev"
Requires-Dist: pytest-xdist>=3.0.0; extra == "dev"
Requires-Dist: fakeredis>=2.10.0; extra == "dev"
Requires-Dist: responses>=0.23.0; extra == "dev"
Requires-Dist: flake8>=6.0.0; extra == "dev"
Requires-Dist: pylint>=2.17.0; extra == "dev"
Requires-Dist: black>=23.0.0; extra == "dev"
Requires-Dist: isort>=5.12.0; extra == "dev"
Requires-Dist: mypy>=1.0.0; extra == "dev"
Requires-Dist: bandit>=1.7.0; extra == "dev"
Requires-Dist: safety>=2.3.0; extra == "dev"
Requires-Dist: pre-commit>=3.0.0; extra == "dev"
Provides-Extra: docs
Requires-Dist: sphinx>=6.0.0; extra == "docs"
Requires-Dist: sphinx-rtd-theme>=1.2.0; extra == "docs"
Requires-Dist: sphinx-autodoc-typehints>=1.23.0; extra == "docs"
Dynamic: license-file
